{"id": "1pqs6b.1", "inputs": [{"text": "At a truck stop, middle of the night.", "tokens": ["at", "a", "truck", "stop", ",", "middle", "of", "the", "night", "."], "pos": ["ADP", "DET", "NOUN", "NOUN", "PUNCT", "NOUN", "ADP", "DET", "NOUN", "PUNCT"], "word_count": 8, "sentence_id": 1}, {"text": "Guy next to me starts talking to me.", "tokens": ["guy", "next", "to", "me", "starts", "talking", "to", "me", "."], "pos": ["PROPN", "ADV", "ADP", "PRON", "VERB", "VERB", "ADP", "PRON", "PUNCT"], "word_count": 8, "sentence_id": 2}, {"text": "He's 50ish, short, friendly, got a bushy mustache.", "tokens": ["he", "'s", "50ish", ",", "short", ",", "friendly", ",", "got", "a", "bushy", "mustache", "."], "pos": ["PRON", "VERB", "ADJ", "PUNCT", "ADJ", "PUNCT", "ADJ", "PUNCT", "VERB", "DET", "ADJ", "NOUN", "PUNCT"], "word_count": 8, "sentence_id": 3}, {"text": "After a moment or two I notice that his mustache is actually his nose hairs which are inches long and obviously combed into the desired mustache shape.", "tokens": ["after", "a", "moment", "or", "two", "i", "notice", "that", "his", "mustache", "is", "actually", "his", "nose", "hairs", "which", "are", "inches", "long", "and", "obviously", "combed", "into", "the", "desired", "mustache", "shape", "."], "pos": ["ADP", "DET", "NOUN", "CCONJ", "NUM", "PRON", "VERB", "ADP", "ADJ", "NOUN", "VERB", "ADV", "ADJ", "NOUN", "NOUN", "ADJ", "VERB", "NOUN", "ADJ", "CCONJ", "ADV", "VERB", "ADP", "DET", "VERB", "NOUN", "NOUN", "PUNCT"], "word_count": 27, "sentence_id": 4}, {"text": "I was both fascinated and repelled at the same time.", "tokens": ["i", "was", "both", "fascinated", "and", "repelled", "at", "the", "same", "time", "."], "pos": ["PRON", "VERB", "DET", "ADJ", "CCONJ", "VERB", "ADP", "DET", "ADJ", "NOUN", "PUNCT"], "word_count": 10, "sentence_id": 5}]}