{"id": "hzqqn.56", "inputs": [{"text": "I actually have a good story about military dogs, and this seems like a good place to tell it.", "tokens": ["i", "actually", "have", "a", "good", "story", "about", "military", "dogs", ",", "and", "this", "seems", "like", "a", "good", "place", "to", "tell", "it", "."], "pos": ["PRON", "ADV", "VERB", "DET", "ADJ", "NOUN", "ADP", "ADJ", "NOUN", "PUNCT", "CCONJ", "DET", "VERB", "ADP", "DET", "ADJ", "NOUN", "PART", "VERB", "PRON", "PUNCT"], "word_count": 19, "sentence_id": 1}, {"text": "Somewhere in Scandanavia, I think it was Sweden, the navy uses dogs when they board boats they suspect are smuggling drugs.", "tokens": ["somewhere", "in", "scandanavia", ",", "i", "think", "it", "was", "sweden", ",", "the", "navy", "uses", "dogs", "when", "they", "board", "boats", "they", "suspect", "are", "smuggling", "drugs", "."], "pos": ["ADV", "ADP", "PROPN", "PUNCT", "PRON", "VERB", "PRON", "VERB", "PROPN", "PUNCT", "DET", "NOUN", "VERB", "NOUN", "ADV", "PRON", "VERB", "NOUN", "PRON", "VERB", "VERB", "VERB", "NOUN", "PUNCT"], "word_count": 21, "sentence_id": 2}, {"text": "The drug runners have a way of countering the dogs; they wear pads around their left arm, and offer it to the dog to clamp on to.", "tokens": ["the", "drug", "runners", "have", "a", "way", "of", "countering", "the", "dogs", ";", "they", "wear", "pads", "around", "their", "left", "arm", ",", "and", "offer", "it", "to", "the", "dog", "to", "clamp", "on", "to", "."], "pos": ["DET", "NOUN", "NOUN", "VERB", "DET", "NOUN", "ADP", "VERB", "DET", "NOUN", "PUNCT", "PRON", "VERB", "NOUN", "ADP", "ADJ", "ADJ", "NOUN", "PUNCT", "CCONJ", "VERB", "PRON", "ADP", "DET", "NOUN", "PART", "VERB", "PART", "ADP", "PUNCT"], "word_count": 27, "sentence_id": 3}, {"text": "When the dog bites, they stab him with their free right hand.", "tokens": ["when", "the", "dog", "bites", ",", "they", "stab", "him", "with", "their", "free", "right", "hand", "."], "pos": ["ADV", "DET", "NOUN", "VERB", "PUNCT", "PRON", "VERB", "PRON", "ADP", "ADJ", "ADJ", "ADJ", "NOUN", "PUNCT"], "word_count": 12, "sentence_id": 4}, {"text": "There was a particular dog by the name of Zeus who was released on one of these boats.", "tokens": ["there", "was", "a", "particular", "dog", "by", "the", "name", "of", "zeus", "who", "was", "released", "on", "one", "of", "these", "boats", "."], "pos": ["ADV", "VERB", "DET", "ADJ", "NOUN", "ADP", "DET", "NOUN", "ADP", "PROPN", "NOUN", "VERB", "VERB", "ADP", "NUM", "ADP", "DET", "NOUN", "PUNCT"], "word_count": 18, "sentence_id": 5}, {"text": "A smuggler tried the padded arm trick, and was subsequently disemboweled by Zeus.", "tokens": ["a", "smuggler", "tried", "the", "padded", "arm", "trick", ",", "and", "was", "subsequently", "disemboweled", "by", "zeus", "."], "pos": ["DET", "NOUN", "VERB", "DET", "ADJ", "NOUN", "NOUN", "PUNCT", "CCONJ", "VERB", "ADV", "VERB", "ADP", "PROPN", "PUNCT"], "word_count": 13, "sentence_id": 6}, {"text": "It's policy that when a police dog kills a human, they are put down.", "tokens": ["it", "'s", "policy", "that", "when", "a", "police", "dog", "kills", "a", "human", ",", "they", "are", "put", "down", "."], "pos": ["PRON", "VERB", "NOUN", "ADP", "ADV", "DET", "NOUN", "NOUN", "VERB", "DET", "NOUN", "PUNCT", "PRON", "VERB", "VERB", "PART", "PUNCT"], "word_count": 14, "sentence_id": 7}, {"text": "I guess the boys didn't like the idea of putting down one of their fellow officers, so Zeus was snuck out of the country and brought to a german shepherd breeder in Canada.", "tokens": ["i", "guess", "the", "boys", "did", "n't", "like", "the", "idea", "of", "putting", "down", "one", "of", "their", "fellow", "officers", ",", "so", "zeus", "was", "snuck", "out", "of", "the", "country", "and", "brought", "to", "a", "german", "shepherd", "breeder", "in", "canada", "."], "pos": ["PRON", "VERB", "DET", "NOUN", "VERB", "ADV", "VERB", "DET", "NOUN", "ADP", "VERB", "PART", "NUM", "ADP", "ADJ", "ADJ", "NOUN", "PUNCT", "ADV", "PROPN", "VERB", "VERB", "ADP", "ADP", "DET", "NOUN", "CCONJ", "VERB", "ADP", "DET", "ADJ", "NOUN", "NOUN", "ADP", "PROPN", "PUNCT"], "word_count": 33, "sentence_id": 8}, {"text": "The American military heard about Zeus, and asked the breeder if she would breed him with one of their Mexican border patrol dogs and ship back the offspring.", "tokens": ["the", "american", "military", "heard", "about", "zeus", ",", "and", "asked", "the", "breeder", "if", "she", "would", "breed", "him", "with", "one", "of", "their", "mexican", "border", "patrol", "dogs", "and", "ship", "back", "the", "offspring", "."], "pos": ["DET", "ADJ", "NOUN", "VERB", "ADP", "PROPN", "PUNCT", "CCONJ", "VERB", "DET", "NOUN", "ADP", "PRON", "VERB", "VERB", "PRON", "ADP", "NUM", "ADP", "ADJ", "ADJ", "NOUN", "NOUN", "NOUN", "CCONJ", "NOUN", "ADV", "DET", "NOUN", "PUNCT"], "word_count": 28, "sentence_id": 9}, {"text": "She agreed, and they shipped up their dog.", "tokens": ["she", "agreed", ",", "and", "they", "shipped", "up", "their", "dog", "."], "pos": ["PRON", "VERB", "PUNCT", "CCONJ", "PRON", "VERB", "PART", "ADJ", "NOUN", "PUNCT"], "word_count": 8, "sentence_id": 10}, {"text": "The breeder said when she got this american dog, it was absolutely out of control, way too aggressive.", "tokens": ["the", "breeder", "said", "when", "she", "got", "this", "american", "dog", ",", "it", "was", "absolutely", "out", "of", "control", ",", "way", "too", "aggressive", "."], "pos": ["DET", "NOUN", "VERB", "ADV", "PRON", "VERB", "DET", "ADJ", "NOUN", "PUNCT", "PRON", "VERB", "ADV", "ADP", "ADP", "NOUN", "PUNCT", "NOUN", "ADV", "ADJ", "PUNCT"], "word_count": 18, "sentence_id": 11}, {"text": "As a responsible breeder, she set to work retraining the dog so it wouldn't be such a danger to people.", "tokens": ["as", "a", "responsible", "breeder", ",", "she", "set", "to", "work", "retraining", "the", "dog", "so", "it", "would", "n't", "be", "such", "a", "danger", "to", "people", "."], "pos": ["ADP", "DET", "ADJ", "NOUN", "PUNCT", "PRON", "VERB", "PART", "VERB", "VERB", "DET", "NOUN", "ADP", "PRON", "VERB", "ADV", "VERB", "ADJ", "DET", "NOUN", "ADP", "NOUN", "PUNCT"], "word_count": 20, "sentence_id": 12}, {"text": "When the Americans asked for their offspring, she refused.", "tokens": ["when", "the", "americans", "asked", "for", "their", "offspring", ",", "she", "refused", "."], "pos": ["ADV", "DET", "PROPN", "VERB", "ADP", "ADJ", "NOUN", "PUNCT", "PRON", "VERB", "PUNCT"], "word_count": 9, "sentence_id": 13}, {"text": "[Zeus' offspring, Max](http://i.imgur.com/kCHrt.jpg) (not with the psycho dog).", "tokens": ["[", "zeus", "'", "offspring", ",", "max](http://i.imgur.com", "/", "kchrt.jpg", ")", "(", "not", "with", "the", "psycho", "dog", ")", "."], "pos": ["PUNCT", "PROPN", "PUNCT", "NOUN", "PUNCT", "X", "SYM", "NOUN", "PUNCT", "PUNCT", "ADV", "ADP", "DET", "ADJ", "NOUN", "PUNCT", "PUNCT"], "word_count": 8, "sentence_id": 14}, {"text": "He's trained in Schutzhund, is incredibly strong and obedient, and he knows secret German commands", "tokens": ["he", "'s", "trained", "in", "schutzhund", ",", "is", "incredibly", "strong", "and", "obedient", ",", "and", "he", "knows", "secret", "german", "commands"], "pos": ["PRON", "VERB", "VERB", "ADP", "PROPN", "PUNCT", "VERB", "ADV", "ADJ", "CCONJ", "ADJ", "PUNCT", "CCONJ", "PRON", "VERB", "ADJ", "ADJ", "NOUN"], "word_count": 15, "sentence_id": 15}]}