{"id": "hzqqn.75", "inputs": [{"text": "When I was in first grade, my dad packed my lunch.", "tokens": ["when", "i", "was", "in", "first", "grade", ",", "my", "dad", "packed", "my", "lunch", "."], "pos": ["ADV", "PRON", "VERB", "ADP", "ADJ", "NOUN", "PUNCT", "ADJ", "NOUN", "VERB", "ADJ", "NOUN", "PUNCT"], "word_count": 11, "sentence_id": 1}, {"text": "He put a ziplock bag of green peppers in there for me to eat raw.", "tokens": ["he", "put", "a", "ziplock", "bag", "of", "green", "peppers", "in", "there", "for", "me", "to", "eat", "raw", "."], "pos": ["PRON", "VERB", "DET", "ADJ", "NOUN", "ADP", "ADJ", "NOUN", "ADP", "ADV", "ADP", "PRON", "PART", "VERB", "ADJ", "PUNCT"], "word_count": 15, "sentence_id": 2}, {"text": "I loved eating them, but I was embarrassed to pull them out at recess when everybody else was eating fruit rollups and crushed ramen noodles.", "tokens": ["i", "loved", "eating", "them", ",", "but", "i", "was", "embarrassed", "to", "pull", "them", "out", "at", "recess", "when", "everybody", "else", "was", "eating", "fruit", "rollups", "and", "crushed", "ramen", "noodles", "."], "pos": ["PRON", "VERB", "VERB", "PRON", "PUNCT", "CCONJ", "PRON", "VERB", "ADJ", "PART", "VERB", "PRON", "PART", "ADP", "NOUN", "ADV", "NOUN", "ADV", "VERB", "VERB", "NOUN", "NOUN", "CCONJ", "ADJ", "NOUN", "NOUN", "PUNCT"], "word_count": 25, "sentence_id": 3}, {"text": "So, when I was alone on the playground, I secretly pulled them out of my lunchpale and stuffed them in my underwear.", "tokens": ["so", ",", "when", "i", "was", "alone", "on", "the", "playground", ",", "i", "secretly", "pulled", "them", "out", "of", "my", "lunchpale", "and", "stuffed", "them", "in", "my", "underwear", "."], "pos": ["CCONJ", "PUNCT", "ADV", "PRON", "VERB", "ADJ", "ADP", "DET", "NOUN", "PUNCT", "PRON", "ADV", "VERB", "PRON", "ADP", "ADP", "ADJ", "NOUN", "CCONJ", "VERB", "PRON", "ADP", "ADJ", "NOUN", "PUNCT"], "word_count": 22, "sentence_id": 4}, {"text": "I didn't want the teacher to see that I hadn't finished my lunch.", "tokens": ["i", "did", "n't", "want", "the", "teacher", "to", "see", "that", "i", "had", "n't", "finished", "my", "lunch", "."], "pos": ["PRON", "VERB", "ADV", "VERB", "DET", "NOUN", "PART", "VERB", "ADP", "PRON", "VERB", "ADV", "VERB", "ADJ", "NOUN", "PUNCT"], "word_count": 13, "sentence_id": 5}, {"text": "All day I was self conscious that she could see the green peppers bulging out of my pants, but I knew I could fool her.", "tokens": ["all", "day", "i", "was", "self", "conscious", "that", "she", "could", "see", "the", "green", "peppers", "bulging", "out", "of", "my", "pants", ",", "but", "i", "knew", "i", "could", "fool", "her", "."], "pos": ["DET", "NOUN", "PRON", "VERB", "NOUN", "ADJ", "ADP", "PRON", "VERB", "VERB", "DET", "ADJ", "NOUN", "VERB", "ADP", "ADP", "ADJ", "NOUN", "PUNCT", "CCONJ", "PRON", "VERB", "PRON", "VERB", "VERB", "PRON", "PUNCT"], "word_count": 25, "sentence_id": 6}, {"text": "She came over to me at one point, kneeled down and said in a very reassuring voice 'Andy, did you hide your green peppers down your pants?", "tokens": ["she", "came", "over", "to", "me", "at", "one", "point", ",", "kneeled", "down", "and", "said", "in", "a", "very", "reassuring", "voice", "'", "andy", ",", "did", "you", "hide", "your", "green", "peppers", "down", "your", "pants", "?"], "pos": ["PRON", "VERB", "PART", "ADP", "PRON", "ADP", "NUM", "NOUN", "PUNCT", "VERB", "PART", "CCONJ", "VERB", "ADP", "DET", "ADV", "ADJ", "NOUN", "PUNCT", "PROPN", "PUNCT", "VERB", "PRON", "VERB", "ADJ", "ADJ", "NOUN", "ADP", "ADJ", "NOUN", "PUNCT"], "word_count": 27, "sentence_id": 7}, {"text": "'", "tokens": ["'"], "pos": ["PUNCT"], "word_count": 1, "sentence_id": 8}, {"text": "I was horrified.", "tokens": ["i", "was", "horrified", "."], "pos": ["PRON", "VERB", "VERB", "PUNCT"], "word_count": 3, "sentence_id": 9}, {"text": "I quickly reassured her that I didn't, and she quickly gave up and left me alone.", "tokens": ["i", "quickly", "reassured", "her", "that", "i", "did", "n't", ",", "and", "she", "quickly", "gave", "up", "and", "left", "me", "alone", "."], "pos": ["PRON", "ADV", "VERB", "PRON", "ADP", "PRON", "VERB", "ADV", "PUNCT", "CCONJ", "PRON", "ADV", "VERB", "PART", "CCONJ", "VERB", "PRON", "ADV", "PUNCT"], "word_count": 16, "sentence_id": 10}, {"text": "For the rest of the day, I tried to think of ways to further prove that I hadn't.", "tokens": ["for", "the", "rest", "of", "the", "day", ",", "i", "tried", "to", "think", "of", "ways", "to", "further", "prove", "that", "i", "had", "n't", "."], "pos": ["ADP", "DET", "NOUN", "ADP", "DET", "NOUN", "PUNCT", "PRON", "VERB", "PART", "VERB", "ADP", "NOUN", "PART", "ADV", "VERB", "ADP", "PRON", "VERB", "ADV", "PUNCT"], "word_count": 18, "sentence_id": 11}, {"text": "I needed to redeem myself.", "tokens": ["i", "needed", "to", "redeem", "myself", "."], "pos": ["PRON", "VERB", "PART", "VERB", "PRON", "PUNCT"], "word_count": 5, "sentence_id": 12}, {"text": "Then, I came up with a brilliant plan.", "tokens": ["then", ",", "i", "came", "up", "with", "a", "brilliant", "plan", "."], "pos": ["ADV", "PUNCT", "PRON", "VERB", "PART", "ADP", "DET", "ADJ", "NOUN", "PUNCT"], "word_count": 8, "sentence_id": 13}, {"text": "I thought to myself 'If I wear the exact same clothes tomorrow, maybe my pants will look exactly the same, and she will *know for sure* that there hadn't been anything in there the day before'.", "tokens": ["i", "thought", "to", "myself", "'", "if", "i", "wear", "the", "exact", "same", "clothes", "tomorrow", ",", "maybe", "my", "pants", "will", "look", "exactly", "the", "same", ",", "and", "she", "will", "*", "know", "for", "sure", "*", "that", "there", "had", "n't", "been", "anything", "in", "there", "the", "day", "before", "'", "."], "pos": ["PRON", "VERB", "ADP", "PRON", "PUNCT", "ADP", "PRON", "VERB", "DET", "ADJ", "ADJ", "NOUN", "NOUN", "PUNCT", "ADV", "ADJ", "NOUN", "VERB", "VERB", "ADV", "DET", "ADJ", "PUNCT", "CCONJ", "PRON", "VERB", "PUNCT", "VERB", "ADP", "ADJ", "PUNCT", "ADP", "ADV", "VERB", "ADV", "VERB", "NOUN", "ADP", "ADV", "DET", "NOUN", "ADP", "PUNCT", "PUNCT"], "word_count": 36, "sentence_id": 14}, {"text": "So, the next day I wore the same outfit, and was confident it looked the same.", "tokens": ["so", ",", "the", "next", "day", "i", "wore", "the", "same", "outfit", ",", "and", "was", "confident", "it", "looked", "the", "same", "."], "pos": ["ADV", "PUNCT", "DET", "ADJ", "NOUN", "PRON", "VERB", "DET", "ADJ", "NOUN", "PUNCT", "CCONJ", "VERB", "ADJ", "PRON", "VERB", "DET", "ADJ", "PUNCT"], "word_count": 16, "sentence_id": 15}, {"text": "I was sure she would notice and understand", "tokens": ["i", "was", "sure", "she", "would", "notice", "and", "understand"], "pos": ["PRON", "VERB", "ADJ", "PRON", "VERB", "VERB", "CCONJ", "VERB"], "word_count": 8, "sentence_id": 16}, {"text": "*that's just how those pants look.", "tokens": ["*", "that", "'s", "just", "how", "those", "pants", "look", "."], "pos": ["PUNCT", "DET", "VERB", "ADV", "ADV", "DET", "NOUN", "VERB", "PUNCT"], "word_count": 6, "sentence_id": 17}, {"text": "*", "tokens": ["*"], "pos": ["PUNCT"], "word_count": 1, "sentence_id": 18}]}