{"id": "pwlhs.26", "inputs": [{"text": "That's incredible, and my story definitely doesn't beat yours, but maybe it will make you feel a little bit better.", "tokens": ["that", "'s", "incredible", ",", "and", "my", "story", "definitely", "does", "n't", "beat", "yours", ",", "but", "maybe", "it", "will", "make", "you", "feel", "a", "little", "bit", "better", "."], "pos": ["DET", "VERB", "ADJ", "PUNCT", "CCONJ", "ADJ", "NOUN", "ADV", "VERB", "ADV", "VERB", "PRON", "PUNCT", "CCONJ", "ADV", "PRON", "VERB", "VERB", "PRON", "VERB", "DET", "ADJ", "NOUN", "ADV", "PUNCT"], "word_count": 20, "sentence_id": 1}, {"text": "When I was senior in high school, I chaperoned a middle school trip for my church, and for a few days everything went better than expected.", "tokens": ["when", "i", "was", "senior", "in", "high", "school", ",", "i", "chaperoned", "a", "middle", "school", "trip", "for", "my", "church", ",", "and", "for", "a", "few", "days", "everything", "went", "better", "than", "expected", "."], "pos": ["ADV", "PRON", "VERB", "ADJ", "ADP", "ADJ", "NOUN", "PUNCT", "PRON", "VERB", "DET", "ADJ", "NOUN", "NOUN", "ADP", "ADJ", "NOUN", "PUNCT", "CCONJ", "ADP", "DET", "ADJ", "NOUN", "NOUN", "VERB", "ADV", "ADP", "VERB", "PUNCT"], "word_count": 26, "sentence_id": 2}, {"text": "The day before we left my stomach started to feel a little queasy, but as I was not in a situation to deal with the problem, I gritted my teeth and waited.", "tokens": ["the", "day", "before", "we", "left", "my", "stomach", "started", "to", "feel", "a", "little", "queasy", ",", "but", "as", "i", "was", "not", "in", "a", "situation", "to", "deal", "with", "the", "problem", ",", "i", "gritted", "my", "teeth", "and", "waited", "."], "pos": ["DET", "NOUN", "ADP", "PRON", "VERB", "ADJ", "NOUN", "VERB", "PART", "VERB", "DET", "ADJ", "NOUN", "PUNCT", "CCONJ", "ADP", "PRON", "VERB", "ADV", "ADP", "DET", "NOUN", "PART", "VERB", "ADP", "DET", "NOUN", "PUNCT", "PRON", "VERB", "ADJ", "NOUN", "CCONJ", "VERB", "PUNCT"], "word_count": 32, "sentence_id": 3}, {"text": "Over an hour later I can finally access the bathroom, but i have some 100 yards between it and me.", "tokens": ["over", "an", "hour", "later", "i", "can", "finally", "access", "the", "bathroom", ",", "but", "i", "have", "some", "100", "yards", "between", "it", "and", "me", "."], "pos": ["ADP", "DET", "NOUN", "ADV", "PRON", "VERB", "ADV", "VERB", "DET", "NOUN", "PUNCT", "CCONJ", "PRON", "VERB", "DET", "NUM", "NOUN", "ADP", "PRON", "CCONJ", "PRON", "PUNCT"], "word_count": 20, "sentence_id": 4}, {"text": "I know I can make it, I know I can make it.", "tokens": ["i", "know", "i", "can", "make", "it", ",", "i", "know", "i", "can", "make", "it", "."], "pos": ["PRON", "VERB", "PRON", "VERB", "VERB", "PRON", "PUNCT", "PRON", "VERB", "PRON", "VERB", "VERB", "PRON", "PUNCT"], "word_count": 12, "sentence_id": 5}, {"text": "I couldn't make it.", "tokens": ["i", "could", "n't", "make", "it", "."], "pos": ["PRON", "VERB", "ADV", "VERB", "PRON", "PUNCT"], "word_count": 4, "sentence_id": 6}, {"text": "15 feet from the door everything went to hell.", "tokens": ["15", "feet", "from", "the", "door", "everything", "went", "to", "hell", "."], "pos": ["NUM", "NOUN", "ADP", "DET", "NOUN", "NOUN", "VERB", "ADP", "NOUN", "PUNCT"], "word_count": 9, "sentence_id": 7}, {"text": "About an hour later I walk out of the bathroom wearing pants that were not my own.", "tokens": ["about", "an", "hour", "later", "i", "walk", "out", "of", "the", "bathroom", "wearing", "pants", "that", "were", "not", "my", "own", "."], "pos": ["ADP", "DET", "NOUN", "ADV", "PRON", "VERB", "ADP", "ADP", "DET", "NOUN", "VERB", "NOUN", "ADJ", "VERB", "ADV", "ADJ", "ADJ", "PUNCT"], "word_count": 17, "sentence_id": 8}, {"text": "As you can imagine word spread like wildfire.", "tokens": ["as", "you", "can", "imagine", "word", "spread", "like", "wildfire", "."], "pos": ["ADP", "PRON", "VERB", "VERB", "NOUN", "VERB", "ADP", "NOUN", "PUNCT"], "word_count": 8, "sentence_id": 9}, {"text": "Like I said, not nearly as bad as yours.", "tokens": ["like", "i", "said", ",", "not", "nearly", "as", "bad", "as", "yours", "."], "pos": ["ADP", "PRON", "VERB", "PUNCT", "ADV", "ADV", "ADV", "ADJ", "ADP", "PRON", "PUNCT"], "word_count": 9, "sentence_id": 10}]}