{"id": "pwlhs.2", "inputs": [{"text": "In Korea the toilets in more rural areas rarely have toilet paper.", "tokens": ["in", "korea", "the", "toilets", "in", "more", "rural", "areas", "rarely", "have", "toilet", "paper", "."], "pos": ["ADP", "PROPN", "DET", "NOUN", "ADP", "ADV", "ADJ", "NOUN", "ADV", "VERB", "NOUN", "NOUN", "PUNCT"], "word_count": 12, "sentence_id": 1}, {"text": "I was 14 visiting family for the summer and had to drop a huge deuce.", "tokens": ["i", "was", "14", "visiting", "family", "for", "the", "summer", "and", "had", "to", "drop", "a", "huge", "deuce", "."], "pos": ["PRON", "VERB", "NUM", "VERB", "NOUN", "ADP", "DET", "NOUN", "CCONJ", "VERB", "PART", "VERB", "DET", "ADJ", "NOUN", "PUNCT"], "word_count": 15, "sentence_id": 2}, {"text": "It came out like gravy; and it was then I realized I had no toilet paper or paper towels in the bathroom.", "tokens": ["it", "came", "out", "like", "gravy", ";", "and", "it", "was", "then", "i", "realized", "i", "had", "no", "toilet", "paper", "or", "paper", "towels", "in", "the", "bathroom", "."], "pos": ["PRON", "VERB", "PART", "ADP", "NOUN", "PUNCT", "CCONJ", "PRON", "VERB", "ADV", "PRON", "VERB", "PRON", "VERB", "DET", "NOUN", "NOUN", "CCONJ", "NOUN", "NOUN", "ADP", "DET", "NOUN", "PUNCT"], "word_count": 22, "sentence_id": 3}, {"text": "Unlike American toilets, most in Korea are the squatters, like this", "tokens": ["unlike", "american", "toilets", ",", "most", "in", "korea", "are", "the", "squatters", ",", "like", "this"], "pos": ["ADP", "ADJ", "NOUN", "PUNCT", "ADJ", "ADP", "PROPN", "VERB", "DET", "NOUN", "PUNCT", "ADP", "DET"], "word_count": 11, "sentence_id": 4}, {"text": "so I couldn't use the toilet water to wipe my ass with my hands:", "tokens": ["so", "i", "could", "n't", "use", "the", "toilet", "water", "to", "wipe", "my", "ass", "with", "my", "hands", ":"], "pos": ["ADP", "PRON", "VERB", "ADV", "VERB", "DET", "NOUN", "NOUN", "PART", "VERB", "ADJ", "NOUN", "ADP", "ADJ", "NOUN", "PUNCT"], "word_count": 14, "sentence_id": 5}, {"text": "http://wanderingcanadian.files.wordpress.com/2008/07/squat-toilet-2.jpg", "tokens": ["http://wanderingcanadian.files.wordpress.com/2008/07/squat-toilet-2.jpg"], "pos": ["NOUN"], "word_count": 1, "sentence_id": 6}, {"text": "There were a shitton of people in the bathroom, and for some retarded reason I decided to use my umbrella I had because it was raining, and I figured the rain would wash it away when I got outside.", "tokens": ["there", "were", "a", "shitton", "of", "people", "in", "the", "bathroom", ",", "and", "for", "some", "retarded", "reason", "i", "decided", "to", "use", "my", "umbrella", "i", "had", "because", "it", "was", "raining", ",", "and", "i", "figured", "the", "rain", "would", "wash", "it", "away", "when", "i", "got", "outside", "."], "pos": ["ADV", "VERB", "DET", "NOUN", "ADP", "NOUN", "ADP", "DET", "NOUN", "PUNCT", "CCONJ", "ADP", "DET", "ADJ", "NOUN", "PRON", "VERB", "PART", "VERB", "ADJ", "NOUN", "PRON", "VERB", "ADP", "PRON", "VERB", "VERB", "PUNCT", "CCONJ", "PRON", "VERB", "DET", "NOUN", "VERB", "VERB", "PRON", "ADV", "ADV", "PRON", "VERB", "ADV", "PUNCT"], "word_count": 39, "sentence_id": 7}, {"text": "When I went outside my aunt grabbed the umbrella, which was the only one we had, and yelled at me for taking so long and opened it up.", "tokens": ["when", "i", "went", "outside", "my", "aunt", "grabbed", "the", "umbrella", ",", "which", "was", "the", "only", "one", "we", "had", ",", "and", "yelled", "at", "me", "for", "taking", "so", "long", "and", "opened", "it", "up", "."], "pos": ["ADV", "PRON", "VERB", "ADP", "ADJ", "NOUN", "VERB", "DET", "NOUN", "PUNCT", "ADJ", "VERB", "DET", "ADJ", "NUM", "PRON", "VERB", "PUNCT", "CCONJ", "VERB", "ADP", "PRON", "ADP", "VERB", "ADV", "ADV", "CCONJ", "VERB", "PRON", "PART", "PUNCT"], "word_count": 28, "sentence_id": 8}, {"text": "Small pieces of my feces flew on my entire family like we were gingerly coated with brown pepper.", "tokens": ["small", "pieces", "of", "my", "feces", "flew", "on", "my", "entire", "family", "like", "we", "were", "gingerly", "coated", "with", "brown", "pepper", "."], "pos": ["ADJ", "NOUN", "ADP", "ADJ", "NOUN", "VERB", "ADP", "ADJ", "ADJ", "NOUN", "ADP", "PRON", "VERB", "ADV", "VERB", "ADP", "ADJ", "NOUN", "PUNCT"], "word_count": 18, "sentence_id": 9}, {"text": "Needless to say I have never returned to Korea", "tokens": ["needless", "to", "say", "i", "have", "never", "returned", "to", "korea"], "pos": ["ADJ", "PART", "VERB", "PRON", "VERB", "ADV", "VERB", "ADP", "PROPN"], "word_count": 9, "sentence_id": 10}]}